openboxes/__init__.py
openboxes/api_client.py
openboxes/configuration.py
openboxes/rest.py
openboxes/api/__init__.py
openboxes/api/authentication_api.py
openboxes/api/configuration_api.py
openboxes/api/location_api.py
openboxes/api/product_api.py
openboxes/api/user_api.py
openboxes/models/__init__.py
openboxes/models/available_item.py
openboxes/models/document.py
openboxes/models/document_type.py
openboxes/models/id_container.py
openboxes/models/inventory.py
openboxes/models/inventory_item.py
openboxes/models/inventory_level.py
openboxes/models/location.py
openboxes/models/location_group.py
openboxes/models/location_list_response.py
openboxes/models/location_type.py
openboxes/models/login_request.py
openboxes/models/organization.py
openboxes/models/party.py
openboxes/models/party_role.py
openboxes/models/party_type.py
openboxes/models/person.py
openboxes/models/person_list_response.py
openboxes/models/product.py
openboxes/models/product_availability.py
openboxes/models/product_availability_and_demand.py
openboxes/models/product_availability_response.py
openboxes/models/product_available_item_response.py
openboxes/models/product_catalog.py
openboxes/models/product_catalog_item.py
openboxes/models/product_demand.py
openboxes/models/product_demand_response.py
openboxes/models/product_group.py
openboxes/models/product_list_response.py
openboxes/models/product_package.py
openboxes/models/product_summary.py
openboxes/models/product_summary_response.py
openboxes/models/product_supplier.py
openboxes/models/role.py
openboxes/models/synonym.py
openboxes/models/synonym_locale.py
openboxes/models/tag.py
openboxes/models/unit_of_measure.py
openboxes/models/unit_of_measure_class.py
openboxes/models/user.py
test/__init__.py
test/test_authentication_api.py
test/test_available_item.py
test/test_configuration_api.py
test/test_document.py
test/test_document_type.py
test/test_id_container.py
test/test_inventory.py
test/test_inventory_item.py
test/test_inventory_level.py
openboxes_client-0.1a2.dist-info/METADATA
openboxes_client-0.1a2.dist-info/WHEEL
openboxes_client-0.1a2.dist-info/top_level.txt
openboxes_client-0.1a2.dist-info/RECORD
